{"runtime_ms":237,"counters":{"PERF_COUNT_HW_CACHE_REFERENCES":18315399,"PERF_COUNT_HW_CACHE_MISSES":12913987,"PERF_COUNT_SW_TASK_CLOCK":1992891166},"energy_samples":[{"duration_ms":237,"energy":[{"pkg":33.35931396484375,"pp0":0,"dram":1.90869140625},{"pkg":33.38677978515625,"pp0":0,"dram":1.3424072265625}]}]}
{"runtime_ms":270,"counters":{"PERF_COUNT_HW_CACHE_REFERENCES":18239565,"PERF_COUNT_HW_CACHE_MISSES":12863024,"PERF_COUNT_SW_TASK_CLOCK":2750012172},"energy_samples":[{"duration_ms":270,"energy":[{"pkg":30.19586181640625,"pp0":0,"dram":2.1617431640625},{"pkg":29.9910888671875,"pp0":0,"dram":1.5185546875}]}]}
{"runtime_ms":318,"counters":{"PERF_COUNT_HW_CACHE_REFERENCES":17253139,"PERF_COUNT_HW_CACHE_MISSES":12749429,"PERF_COUNT_SW_TASK_CLOCK":2114615101},"energy_samples":[{"duration_ms":318,"energy":[{"pkg":30.04144287109375,"pp0":0,"dram":2.52313232421875},{"pkg":30.09130859375,"pp0":0,"dram":1.79437255859375}]}]}
{"runtime_ms":326,"counters":{"PERF_COUNT_HW_CACHE_REFERENCES":18497920,"PERF_COUNT_HW_CACHE_MISSES":12947267,"PERF_COUNT_SW_TASK_CLOCK":2918914242},"energy_samples":[{"duration_ms":327,"energy":[{"pkg":30.9014892578125,"pp0":0,"dram":2.5989990234375},{"pkg":30.34503173828125,"pp0":0,"dram":1.82818603515625}]}]}
{"runtime_ms":321,"counters":{"PERF_COUNT_HW_CACHE_REFERENCES":16937079,"PERF_COUNT_HW_CACHE_MISSES":12736644,"PERF_COUNT_SW_TASK_CLOCK":2242623371},"energy_samples":[{"duration_ms":321,"energy":[{"pkg":30.52239990234375,"pp0":0,"dram":2.5540771484375},{"pkg":29.8765869140625,"pp0":0,"dram":1.79827880859375}]}]}
{"runtime_ms":199,"counters":{"PERF_COUNT_HW_CACHE_REFERENCES":17530948,"PERF_COUNT_HW_CACHE_MISSES":12744861,"PERF_COUNT_SW_TASK_CLOCK":1638461766},"energy_samples":[{"duration_ms":200,"energy":[{"pkg":27.58111572265625,"pp0":0,"dram":1.62713623046875},{"pkg":24.94073486328125,"pp0":0,"dram":1.1322021484375}]}]}
{"runtime_ms":245,"counters":{"PERF_COUNT_HW_CACHE_REFERENCES":20567266,"PERF_COUNT_HW_CACHE_MISSES":13170518,"PERF_COUNT_SW_TASK_CLOCK":2237521080},"energy_samples":[{"duration_ms":245,"energy":[{"pkg":35.5501708984375,"pp0":0,"dram":1.95703125},{"pkg":35.4603271484375,"pp0":0,"dram":1.37933349609375}]}]}
{"runtime_ms":177,"counters":{"PERF_COUNT_HW_CACHE_REFERENCES":16731234,"PERF_COUNT_HW_CACHE_MISSES":12522315,"PERF_COUNT_SW_TASK_CLOCK":1429710344},"energy_samples":[{"duration_ms":178,"energy":[{"pkg":29.08197021484375,"pp0":0,"dram":1.45465087890625},{"pkg":26.17742919921875,"pp0":0,"dram":1.0003662109375}]}]}
{"runtime_ms":250,"counters":{"PERF_COUNT_HW_CACHE_REFERENCES":19474995,"PERF_COUNT_HW_CACHE_MISSES":13986213,"PERF_COUNT_SW_TASK_CLOCK":2003702435},"energy_samples":[{"duration_ms":251,"energy":[{"pkg":40.685302734375,"pp0":0,"dram":1.88751220703125},{"pkg":39.9345703125,"pp0":0,"dram":1.6617431640625}]}]}
{"runtime_ms":192,"counters":{"PERF_COUNT_HW_CACHE_REFERENCES":17689188,"PERF_COUNT_HW_CACHE_MISSES":13346374,"PERF_COUNT_SW_TASK_CLOCK":1681559762},"energy_samples":[{"duration_ms":192,"energy":[{"pkg":32.35943603515625,"pp0":0,"dram":1.7496337890625},{"pkg":30.01202392578125,"pp0":0,"dram":1.1070556640625}]}]}
{"runtime_ms":193,"counters":{"PERF_COUNT_HW_CACHE_REFERENCES":18491751,"PERF_COUNT_HW_CACHE_MISSES":13036960,"PERF_COUNT_SW_TASK_CLOCK":1788904619},"energy_samples":[{"duration_ms":193,"energy":[{"pkg":32.8848876953125,"pp0":0,"dram":1.56646728515625},{"pkg":30.8760986328125,"pp0":0,"dram":1.09295654296875}]}]}
{"runtime_ms":238,"counters":{"PERF_COUNT_HW_CACHE_REFERENCES":18404689,"PERF_COUNT_HW_CACHE_MISSES":12836740,"PERF_COUNT_SW_TASK_CLOCK":1773209078},"energy_samples":[{"duration_ms":238,"energy":[{"pkg":35.3203125,"pp0":0,"dram":1.9052734375},{"pkg":35.8773193359375,"pp0":0,"dram":1.34521484375}]}]}
{"runtime_ms":249,"counters":{"PERF_COUNT_HW_CACHE_REFERENCES":18672850,"PERF_COUNT_HW_CACHE_MISSES":12935482,"PERF_COUNT_SW_TASK_CLOCK":2134346540},"energy_samples":[{"duration_ms":249,"energy":[{"pkg":32.73931884765625,"pp0":0,"dram":2.00775146484375},{"pkg":33.13507080078125,"pp0":0,"dram":1.40216064453125}]}]}
{"runtime_ms":184,"counters":{"PERF_COUNT_HW_CACHE_REFERENCES":18188709,"PERF_COUNT_HW_CACHE_MISSES":12888761,"PERF_COUNT_SW_TASK_CLOCK":1458954296},"energy_samples":[{"duration_ms":184,"energy":[{"pkg":30.259033203125,"pp0":0,"dram":1.504638671875},{"pkg":27.48883056640625,"pp0":0,"dram":1.04248046875}]}]}
{"runtime_ms":205,"counters":{"PERF_COUNT_HW_CACHE_REFERENCES":19438659,"PERF_COUNT_HW_CACHE_MISSES":13843957,"PERF_COUNT_SW_TASK_CLOCK":2146294407},"energy_samples":[{"duration_ms":205,"energy":[{"pkg":33.46368408203125,"pp0":0,"dram":1.55780029296875},{"pkg":34.16900634765625,"pp0":0,"dram":1.4652099609375}]}]}
{"runtime_ms":191,"counters":{"PERF_COUNT_HW_CACHE_REFERENCES":18527675,"PERF_COUNT_HW_CACHE_MISSES":13366408,"PERF_COUNT_SW_TASK_CLOCK":1879184716},"energy_samples":[{"duration_ms":192,"energy":[{"pkg":32.6201171875,"pp0":0,"dram":1.74560546875},{"pkg":30.0286865234375,"pp0":0,"dram":1.109375}]}]}
{"runtime_ms":196,"counters":{"PERF_COUNT_HW_CACHE_REFERENCES":18340542,"PERF_COUNT_HW_CACHE_MISSES":12971770,"PERF_COUNT_SW_TASK_CLOCK":1827085132},"energy_samples":[{"duration_ms":196,"energy":[{"pkg":33.29046630859375,"pp0":0,"dram":1.5887451171875},{"pkg":30.4417724609375,"pp0":0,"dram":1.1126708984375}]}]}
{"runtime_ms":190,"counters":{"PERF_COUNT_HW_CACHE_REFERENCES":18308866,"PERF_COUNT_HW_CACHE_MISSES":12973909,"PERF_COUNT_SW_TASK_CLOCK":1619544422},"energy_samples":[{"duration_ms":190,"energy":[{"pkg":32.537841796875,"pp0":0,"dram":1.55364990234375},{"pkg":30.01593017578125,"pp0":0,"dram":1.0836181640625}]}]}
{"runtime_ms":190,"counters":{"PERF_COUNT_HW_CACHE_REFERENCES":17996754,"PERF_COUNT_HW_CACHE_MISSES":12862809,"PERF_COUNT_SW_TASK_CLOCK":1586679375},"energy_samples":[{"duration_ms":191,"energy":[{"pkg":32.76739501953125,"pp0":0,"dram":1.57171630859375},{"pkg":29.5322265625,"pp0":0,"dram":1.0794677734375}]}]}
{"runtime_ms":191,"counters":{"PERF_COUNT_HW_CACHE_REFERENCES":19220353,"PERF_COUNT_HW_CACHE_MISSES":13094976,"PERF_COUNT_SW_TASK_CLOCK":1864082772},"energy_samples":[{"duration_ms":192,"energy":[{"pkg":32.84637451171875,"pp0":0,"dram":1.572021484375},{"pkg":29.50762939453125,"pp0":0,"dram":1.089111328125}]}]}
{"runtime_ms":196,"counters":{"PERF_COUNT_HW_CACHE_REFERENCES":21081723,"PERF_COUNT_HW_CACHE_MISSES":13418115,"PERF_COUNT_SW_TASK_CLOCK":2381333355},"energy_samples":[{"duration_ms":196,"energy":[{"pkg":33.61260986328125,"pp0":0,"dram":1.60491943359375},{"pkg":30.82818603515625,"pp0":0,"dram":1.11676025390625}]}]}
