{"runtime":14016,"energy":{"pkg":935.5484008789062,"pp0":0,"dram":151.83367919921875},"rusage":{"ru_utime":{"tv_sec":77,"tv_usec":291201},"ru_stime":{"tv_sec":0,"tv_usec":487479},"ru_maxrss":260096,"ru_ixrss":0,"ru_idrss":0,"ru_isrss":0,"ru_minflt":138907,"ru_majflt":0,"ru_nswap":0,"ru_inblock":0,"ru_oublock":0,"ru_msgsnd":0,"ru_msgrcv":0,"ru_nsignals":0,"ru_nvcsw":16,"ru_nivcsw":7779}}
{"runtime":14428,"energy":{"pkg":950.428466796875,"pp0":0,"dram":154.79193115234375},"rusage":{"ru_utime":{"tv_sec":78,"tv_usec":938170},"ru_stime":{"tv_sec":0,"tv_usec":467507},"ru_maxrss":260304,"ru_ixrss":0,"ru_idrss":0,"ru_isrss":0,"ru_minflt":138913,"ru_majflt":0,"ru_nswap":0,"ru_inblock":0,"ru_oublock":0,"ru_msgsnd":0,"ru_msgrcv":0,"ru_nsignals":0,"ru_nvcsw":16,"ru_nivcsw":7941}}
{"runtime":14514,"energy":{"pkg":941.156005859375,"pp0":0,"dram":156.11102294921875},"rusage":{"ru_utime":{"tv_sec":79,"tv_usec":556775},"ru_stime":{"tv_sec":0,"tv_usec":437111},"ru_maxrss":260152,"ru_ixrss":0,"ru_idrss":0,"ru_isrss":0,"ru_minflt":138916,"ru_majflt":0,"ru_nswap":0,"ru_inblock":0,"ru_oublock":0,"ru_msgsnd":0,"ru_msgrcv":0,"ru_nsignals":0,"ru_nvcsw":16,"ru_nivcsw":8068}}
{"runtime":14443,"energy":{"pkg":945.8793334960938,"pp0":0,"dram":154.64996337890625},"rusage":{"ru_utime":{"tv_sec":79,"tv_usec":224598},"ru_stime":{"tv_sec":0,"tv_usec":437332},"ru_maxrss":260208,"ru_ixrss":0,"ru_idrss":0,"ru_isrss":0,"ru_minflt":138921,"ru_majflt":0,"ru_nswap":0,"ru_inblock":0,"ru_oublock":0,"ru_msgsnd":0,"ru_msgrcv":0,"ru_nsignals":0,"ru_nvcsw":16,"ru_nivcsw":7927}}
{"runtime":14526,"energy":{"pkg":954.7101440429688,"pp0":0,"dram":157.11328125},"rusage":{"ru_utime":{"tv_sec":78,"tv_usec":479652},"ru_stime":{"tv_sec":0,"tv_usec":463880},"ru_maxrss":260204,"ru_ixrss":0,"ru_idrss":0,"ru_isrss":0,"ru_minflt":138919,"ru_majflt":0,"ru_nswap":0,"ru_inblock":0,"ru_oublock":0,"ru_msgsnd":0,"ru_msgrcv":0,"ru_nsignals":0,"ru_nvcsw":15,"ru_nivcsw":7859}}
{"runtime":13297,"energy":{"pkg":933.3484497070312,"pp0":0,"dram":148.97637939453125},"rusage":{"ru_utime":{"tv_sec":74,"tv_usec":819603},"ru_stime":{"tv_sec":0,"tv_usec":371990},"ru_maxrss":260204,"ru_ixrss":0,"ru_idrss":0,"ru_isrss":0,"ru_minflt":138909,"ru_majflt":0,"ru_nswap":0,"ru_inblock":0,"ru_oublock":0,"ru_msgsnd":0,"ru_msgrcv":0,"ru_nsignals":0,"ru_nvcsw":16,"ru_nivcsw":7498}}
{"runtime":14476,"energy":{"pkg":952.017333984375,"pp0":0,"dram":154.73406982421875},"rusage":{"ru_utime":{"tv_sec":79,"tv_usec":566902},"ru_stime":{"tv_sec":0,"tv_usec":523226},"ru_maxrss":260316,"ru_ixrss":0,"ru_idrss":0,"ru_isrss":0,"ru_minflt":138916,"ru_majflt":0,"ru_nswap":0,"ru_inblock":0,"ru_oublock":0,"ru_msgsnd":0,"ru_msgrcv":0,"ru_nsignals":0,"ru_nvcsw":16,"ru_nivcsw":8031}}
{"runtime":15060,"energy":{"pkg":991.6326293945312,"pp0":0,"dram":164.2698974609375},"rusage":{"ru_utime":{"tv_sec":77,"tv_usec":438562},"ru_stime":{"tv_sec":0,"tv_usec":441024},"ru_maxrss":260204,"ru_ixrss":0,"ru_idrss":0,"ru_isrss":0,"ru_minflt":138923,"ru_majflt":0,"ru_nswap":0,"ru_inblock":0,"ru_oublock":0,"ru_msgsnd":0,"ru_msgrcv":0,"ru_nsignals":0,"ru_nvcsw":16,"ru_nivcsw":7784}}
{"runtime":13356,"energy":{"pkg":939.631591796875,"pp0":0,"dram":149.40155029296875},"rusage":{"ru_utime":{"tv_sec":74,"tv_usec":791839},"ru_stime":{"tv_sec":0,"tv_usec":403881},"ru_maxrss":260008,"ru_ixrss":0,"ru_idrss":0,"ru_isrss":0,"ru_minflt":138884,"ru_majflt":0,"ru_nswap":0,"ru_inblock":0,"ru_oublock":0,"ru_msgsnd":0,"ru_msgrcv":0,"ru_nsignals":0,"ru_nvcsw":16,"ru_nivcsw":7533}}
{"runtime":15591,"energy":{"pkg":998.27392578125,"pp0":0,"dram":171.2244873046875},"rusage":{"ru_utime":{"tv_sec":81,"tv_usec":175099},"ru_stime":{"tv_sec":0,"tv_usec":491907},"ru_maxrss":260216,"ru_ixrss":0,"ru_idrss":0,"ru_isrss":0,"ru_minflt":142962,"ru_majflt":0,"ru_nswap":0,"ru_inblock":0,"ru_oublock":0,"ru_msgsnd":0,"ru_msgrcv":0,"ru_nsignals":0,"ru_nvcsw":16,"ru_nivcsw":8156}}
{"runtime":13264,"energy":{"pkg":944.2047729492188,"pp0":0,"dram":144.50054931640625},"rusage":{"ru_utime":{"tv_sec":74,"tv_usec":731175},"ru_stime":{"tv_sec":0,"tv_usec":431670},"ru_maxrss":260308,"ru_ixrss":0,"ru_idrss":0,"ru_isrss":0,"ru_minflt":138917,"ru_majflt":0,"ru_nswap":0,"ru_inblock":0,"ru_oublock":0,"ru_msgsnd":0,"ru_msgrcv":0,"ru_nsignals":0,"ru_nvcsw":16,"ru_nivcsw":7572}}
{"runtime":14465,"energy":{"pkg":957.3631591796875,"pp0":0,"dram":156.3211669921875},"rusage":{"ru_utime":{"tv_sec":79,"tv_usec":955297},"ru_stime":{"tv_sec":0,"tv_usec":475592},"ru_maxrss":260312,"ru_ixrss":0,"ru_idrss":0,"ru_isrss":0,"ru_minflt":138901,"ru_majflt":0,"ru_nswap":0,"ru_inblock":0,"ru_oublock":0,"ru_msgsnd":0,"ru_msgrcv":0,"ru_nsignals":0,"ru_nvcsw":16,"ru_nivcsw":8080}}
{"runtime":14230,"energy":{"pkg":948.5553588867188,"pp0":0,"dram":153.60296630859375},"rusage":{"ru_utime":{"tv_sec":78,"tv_usec":36016},"ru_stime":{"tv_sec":0,"tv_usec":441100},"ru_maxrss":260240,"ru_ixrss":0,"ru_idrss":0,"ru_isrss":0,"ru_minflt":138904,"ru_majflt":0,"ru_nswap":0,"ru_inblock":0,"ru_oublock":0,"ru_msgsnd":0,"ru_msgrcv":0,"ru_nsignals":0,"ru_nvcsw":16,"ru_nivcsw":7876}}
{"runtime":14014,"energy":{"pkg":956.1021118164062,"pp0":0,"dram":152.2825927734375},"rusage":{"ru_utime":{"tv_sec":77,"tv_usec":776913},"ru_stime":{"tv_sec":0,"tv_usec":429171},"ru_maxrss":260252,"ru_ixrss":0,"ru_idrss":0,"ru_isrss":0,"ru_minflt":138889,"ru_majflt":0,"ru_nswap":0,"ru_inblock":0,"ru_oublock":0,"ru_msgsnd":0,"ru_msgrcv":0,"ru_nsignals":0,"ru_nvcsw":16,"ru_nivcsw":7808}}
{"runtime":14103,"energy":{"pkg":953.2275390625,"pp0":0,"dram":152.0384521484375},"rusage":{"ru_utime":{"tv_sec":79,"tv_usec":33528},"ru_stime":{"tv_sec":0,"tv_usec":395689},"ru_maxrss":260108,"ru_ixrss":0,"ru_idrss":0,"ru_isrss":0,"ru_minflt":138912,"ru_majflt":0,"ru_nswap":0,"ru_inblock":0,"ru_oublock":0,"ru_msgsnd":0,"ru_msgrcv":0,"ru_nsignals":0,"ru_nvcsw":15,"ru_nivcsw":7974}}
{"runtime":14633,"energy":{"pkg":953.0734252929688,"pp0":0,"dram":157.6285400390625},"rusage":{"ru_utime":{"tv_sec":79,"tv_usec":794614},"ru_stime":{"tv_sec":0,"tv_usec":456805},"ru_maxrss":260240,"ru_ixrss":0,"ru_idrss":0,"ru_isrss":0,"ru_minflt":138898,"ru_majflt":0,"ru_nswap":0,"ru_inblock":0,"ru_oublock":0,"ru_msgsnd":0,"ru_msgrcv":0,"ru_nsignals":0,"ru_nvcsw":16,"ru_nivcsw":8020}}
{"runtime":13414,"energy":{"pkg":940.7820434570312,"pp0":0,"dram":149.77215576171875},"rusage":{"ru_utime":{"tv_sec":75,"tv_usec":315084},"ru_stime":{"tv_sec":0,"tv_usec":407932},"ru_maxrss":260212,"ru_ixrss":0,"ru_idrss":0,"ru_isrss":0,"ru_minflt":138923,"ru_majflt":0,"ru_nswap":0,"ru_inblock":0,"ru_oublock":0,"ru_msgsnd":0,"ru_msgrcv":0,"ru_nsignals":0,"ru_nvcsw":16,"ru_nivcsw":7558}}
{"runtime":13895,"energy":{"pkg":945.203125,"pp0":0,"dram":150.229736328125},"rusage":{"ru_utime":{"tv_sec":78,"tv_usec":897948},"ru_stime":{"tv_sec":0,"tv_usec":405085},"ru_maxrss":260200,"ru_ixrss":0,"ru_idrss":0,"ru_isrss":0,"ru_minflt":138907,"ru_majflt":0,"ru_nswap":0,"ru_inblock":0,"ru_oublock":0,"ru_msgsnd":0,"ru_msgrcv":0,"ru_nsignals":0,"ru_nvcsw":16,"ru_nivcsw":7928}}
{"runtime":14480,"energy":{"pkg":947.3731689453125,"pp0":0,"dram":153.48394775390625},"rusage":{"ru_utime":{"tv_sec":79,"tv_usec":661840},"ru_stime":{"tv_sec":0,"tv_usec":455785},"ru_maxrss":260076,"ru_ixrss":0,"ru_idrss":0,"ru_isrss":0,"ru_minflt":138887,"ru_majflt":0,"ru_nswap":0,"ru_inblock":0,"ru_oublock":0,"ru_msgsnd":0,"ru_msgrcv":0,"ru_nsignals":0,"ru_nvcsw":15,"ru_nivcsw":7975}}
{"runtime":14432,"energy":{"pkg":955.0381469726562,"pp0":0,"dram":158.91717529296875},"rusage":{"ru_utime":{"tv_sec":79,"tv_usec":508079},"ru_stime":{"tv_sec":0,"tv_usec":420967},"ru_maxrss":260156,"ru_ixrss":0,"ru_idrss":0,"ru_isrss":0,"ru_minflt":138917,"ru_majflt":0,"ru_nswap":0,"ru_inblock":0,"ru_oublock":0,"ru_msgsnd":0,"ru_msgrcv":0,"ru_nsignals":0,"ru_nvcsw":16,"ru_nivcsw":7989}}
{"runtime":14335,"energy":{"pkg":945.4898071289062,"pp0":0,"dram":153.57452392578125},"rusage":{"ru_utime":{"tv_sec":79,"tv_usec":495782},"ru_stime":{"tv_sec":0,"tv_usec":456890},"ru_maxrss":260152,"ru_ixrss":0,"ru_idrss":0,"ru_isrss":0,"ru_minflt":138915,"ru_majflt":0,"ru_nswap":0,"ru_inblock":0,"ru_oublock":0,"ru_msgsnd":0,"ru_msgrcv":0,"ru_nsignals":0,"ru_nvcsw":16,"ru_nivcsw":7987}}
