{"runtime":5168,"energy":{"pkg":264.7939453125,"pp0":0,"dram":66.18701171875},"rusage":{"ru_utime":{"tv_sec":16,"tv_usec":87418},"ru_stime":{"tv_sec":0,"tv_usec":112018},"ru_maxrss":3816,"ru_ixrss":0,"ru_idrss":0,"ru_isrss":0,"ru_minflt":262,"ru_majflt":0,"ru_nswap":0,"ru_inblock":0,"ru_oublock":0,"ru_msgsnd":0,"ru_msgrcv":0,"ru_nsignals":0,"ru_nvcsw":15,"ru_nivcsw":148314}}
{"runtime":3230,"energy":{"pkg":167.59552001953125,"pp0":0,"dram":43.94573974609375},"rusage":{"ru_utime":{"tv_sec":12,"tv_usec":67201},"ru_stime":{"tv_sec":0,"tv_usec":45212},"ru_maxrss":3844,"ru_ixrss":0,"ru_idrss":0,"ru_isrss":0,"ru_minflt":268,"ru_majflt":0,"ru_nswap":0,"ru_inblock":0,"ru_oublock":0,"ru_msgsnd":0,"ru_msgrcv":0,"ru_nsignals":0,"ru_nvcsw":22,"ru_nivcsw":57444}}
{"runtime":3233,"energy":{"pkg":165.884765625,"pp0":0,"dram":44.02691650390625},"rusage":{"ru_utime":{"tv_sec":11,"tv_usec":566388},"ru_stime":{"tv_sec":0,"tv_usec":8000},"ru_maxrss":3824,"ru_ixrss":0,"ru_idrss":0,"ru_isrss":0,"ru_minflt":271,"ru_majflt":0,"ru_nswap":0,"ru_inblock":0,"ru_oublock":0,"ru_msgsnd":0,"ru_msgrcv":0,"ru_nsignals":0,"ru_nvcsw":16,"ru_nivcsw":36259}}
{"runtime":4291,"energy":{"pkg":221.8868408203125,"pp0":0,"dram":55.77130126953125},"rusage":{"ru_utime":{"tv_sec":13,"tv_usec":996994},"ru_stime":{"tv_sec":0,"tv_usec":107998},"ru_maxrss":3684,"ru_ixrss":0,"ru_idrss":0,"ru_isrss":0,"ru_minflt":260,"ru_majflt":0,"ru_nswap":0,"ru_inblock":0,"ru_oublock":0,"ru_msgsnd":0,"ru_msgrcv":0,"ru_nsignals":0,"ru_nvcsw":17,"ru_nivcsw":108651}}
{"runtime":3013,"energy":{"pkg":154.598876953125,"pp0":0,"dram":40.8218994140625},"rusage":{"ru_utime":{"tv_sec":10,"tv_usec":948064},"ru_stime":{"tv_sec":0,"tv_usec":20005},"ru_maxrss":3844,"ru_ixrss":0,"ru_idrss":0,"ru_isrss":0,"ru_minflt":270,"ru_majflt":0,"ru_nswap":0,"ru_inblock":0,"ru_oublock":0,"ru_msgsnd":0,"ru_msgrcv":0,"ru_nsignals":0,"ru_nvcsw":24,"ru_nivcsw":16172}}
{"runtime":3239,"energy":{"pkg":165.24298095703125,"pp0":0,"dram":43.92120361328125},"rusage":{"ru_utime":{"tv_sec":11,"tv_usec":961985},"ru_stime":{"tv_sec":0,"tv_usec":28743},"ru_maxrss":3848,"ru_ixrss":0,"ru_idrss":0,"ru_isrss":0,"ru_minflt":267,"ru_majflt":0,"ru_nswap":0,"ru_inblock":0,"ru_oublock":0,"ru_msgsnd":0,"ru_msgrcv":0,"ru_nsignals":0,"ru_nvcsw":17,"ru_nivcsw":38106}}
{"runtime":3902,"energy":{"pkg":201.70477294921875,"pp0":0,"dram":50.31903076171875},"rusage":{"ru_utime":{"tv_sec":12,"tv_usec":705405},"ru_stime":{"tv_sec":0,"tv_usec":56000},"ru_maxrss":3840,"ru_ixrss":0,"ru_idrss":0,"ru_isrss":0,"ru_minflt":265,"ru_majflt":0,"ru_nswap":0,"ru_inblock":0,"ru_oublock":0,"ru_msgsnd":0,"ru_msgrcv":0,"ru_nsignals":0,"ru_nvcsw":22,"ru_nivcsw":86174}}
{"runtime":3810,"energy":{"pkg":197.0643310546875,"pp0":0,"dram":53.1702880859375},"rusage":{"ru_utime":{"tv_sec":12,"tv_usec":894359},"ru_stime":{"tv_sec":0,"tv_usec":68006},"ru_maxrss":3884,"ru_ixrss":0,"ru_idrss":0,"ru_isrss":0,"ru_minflt":261,"ru_majflt":0,"ru_nswap":0,"ru_inblock":0,"ru_oublock":0,"ru_msgsnd":0,"ru_msgrcv":0,"ru_nsignals":0,"ru_nvcsw":20,"ru_nivcsw":78403}}
{"runtime":4111,"energy":{"pkg":211.30120849609375,"pp0":0,"dram":58.42706298828125},"rusage":{"ru_utime":{"tv_sec":13,"tv_usec":573778},"ru_stime":{"tv_sec":0,"tv_usec":40001},"ru_maxrss":3684,"ru_ixrss":0,"ru_idrss":0,"ru_isrss":0,"ru_minflt":264,"ru_majflt":0,"ru_nswap":0,"ru_inblock":0,"ru_oublock":0,"ru_msgsnd":0,"ru_msgrcv":0,"ru_nsignals":0,"ru_nvcsw":13,"ru_nivcsw":71296}}
{"runtime":3524,"energy":{"pkg":185.347412109375,"pp0":0,"dram":48.10394287109375},"rusage":{"ru_utime":{"tv_sec":13,"tv_usec":853492},"ru_stime":{"tv_sec":0,"tv_usec":76001},"ru_maxrss":3860,"ru_ixrss":0,"ru_idrss":0,"ru_isrss":0,"ru_minflt":289,"ru_majflt":0,"ru_nswap":0,"ru_inblock":0,"ru_oublock":0,"ru_msgsnd":0,"ru_msgrcv":0,"ru_nsignals":0,"ru_nvcsw":21,"ru_nivcsw":57210}}
{"runtime":4652,"energy":{"pkg":238.3328857421875,"pp0":0,"dram":61.86236572265625},"rusage":{"ru_utime":{"tv_sec":14,"tv_usec":701821},"ru_stime":{"tv_sec":0,"tv_usec":139968},"ru_maxrss":3948,"ru_ixrss":0,"ru_idrss":0,"ru_isrss":0,"ru_minflt":269,"ru_majflt":0,"ru_nswap":0,"ru_inblock":0,"ru_oublock":0,"ru_msgsnd":0,"ru_msgrcv":0,"ru_nsignals":0,"ru_nvcsw":22,"ru_nivcsw":110421}}
{"runtime":3882,"energy":{"pkg":198.61529541015625,"pp0":0,"dram":51.343994140625},"rusage":{"ru_utime":{"tv_sec":12,"tv_usec":782233},"ru_stime":{"tv_sec":0,"tv_usec":47976},"ru_maxrss":3828,"ru_ixrss":0,"ru_idrss":0,"ru_isrss":0,"ru_minflt":266,"ru_majflt":0,"ru_nswap":0,"ru_inblock":0,"ru_oublock":0,"ru_msgsnd":0,"ru_msgrcv":0,"ru_nsignals":0,"ru_nvcsw":18,"ru_nivcsw":82895}}
{"runtime":4281,"energy":{"pkg":218.9412841796875,"pp0":0,"dram":55.13336181640625},"rusage":{"ru_utime":{"tv_sec":13,"tv_usec":750115},"ru_stime":{"tv_sec":0,"tv_usec":111975},"ru_maxrss":3848,"ru_ixrss":0,"ru_idrss":0,"ru_isrss":0,"ru_minflt":264,"ru_majflt":0,"ru_nswap":0,"ru_inblock":0,"ru_oublock":0,"ru_msgsnd":0,"ru_msgrcv":0,"ru_nsignals":0,"ru_nvcsw":21,"ru_nivcsw":115144}}
{"runtime":4412,"energy":{"pkg":229.9044189453125,"pp0":0,"dram":56.08941650390625},"rusage":{"ru_utime":{"tv_sec":14,"tv_usec":612783},"ru_stime":{"tv_sec":0,"tv_usec":112001},"ru_maxrss":3952,"ru_ixrss":0,"ru_idrss":0,"ru_isrss":0,"ru_minflt":270,"ru_majflt":0,"ru_nswap":0,"ru_inblock":0,"ru_oublock":0,"ru_msgsnd":0,"ru_msgrcv":0,"ru_nsignals":0,"ru_nvcsw":12,"ru_nivcsw":125907}}
{"runtime":4659,"energy":{"pkg":235.08770751953125,"pp0":0,"dram":62.433349609375},"rusage":{"ru_utime":{"tv_sec":13,"tv_usec":892114},"ru_stime":{"tv_sec":0,"tv_usec":156032},"ru_maxrss":3840,"ru_ixrss":0,"ru_idrss":0,"ru_isrss":0,"ru_minflt":289,"ru_majflt":0,"ru_nswap":0,"ru_inblock":0,"ru_oublock":0,"ru_msgsnd":0,"ru_msgrcv":0,"ru_nsignals":0,"ru_nvcsw":28,"ru_nivcsw":93018}}
{"runtime":4240,"energy":{"pkg":214.43585205078125,"pp0":0,"dram":54.98626708984375},"rusage":{"ru_utime":{"tv_sec":13,"tv_usec":461257},"ru_stime":{"tv_sec":0,"tv_usec":75976},"ru_maxrss":3952,"ru_ixrss":0,"ru_idrss":0,"ru_isrss":0,"ru_minflt":267,"ru_majflt":0,"ru_nswap":0,"ru_inblock":0,"ru_oublock":0,"ru_msgsnd":0,"ru_msgrcv":0,"ru_nsignals":0,"ru_nvcsw":17,"ru_nivcsw":81777}}
{"runtime":4321,"energy":{"pkg":223.41693115234375,"pp0":0,"dram":53.936279296875},"rusage":{"ru_utime":{"tv_sec":13,"tv_usec":364722},"ru_stime":{"tv_sec":0,"tv_usec":116030},"ru_maxrss":3808,"ru_ixrss":0,"ru_idrss":0,"ru_isrss":0,"ru_minflt":269,"ru_majflt":0,"ru_nswap":0,"ru_inblock":0,"ru_oublock":0,"ru_msgsnd":0,"ru_msgrcv":0,"ru_nsignals":0,"ru_nvcsw":23,"ru_nivcsw":130510}}
{"runtime":3969,"energy":{"pkg":206.7265625,"pp0":0,"dram":52.14007568359375},"rusage":{"ru_utime":{"tv_sec":12,"tv_usec":811998},"ru_stime":{"tv_sec":0,"tv_usec":87993},"ru_maxrss":3848,"ru_ixrss":0,"ru_idrss":0,"ru_isrss":0,"ru_minflt":262,"ru_majflt":0,"ru_nswap":0,"ru_inblock":0,"ru_oublock":0,"ru_msgsnd":0,"ru_msgrcv":0,"ru_nsignals":0,"ru_nvcsw":12,"ru_nivcsw":102463}}
{"runtime":3644,"energy":{"pkg":191.25164794921875,"pp0":0,"dram":48.355712890625},"rusage":{"ru_utime":{"tv_sec":12,"tv_usec":705891},"ru_stime":{"tv_sec":0,"tv_usec":105163},"ru_maxrss":3856,"ru_ixrss":0,"ru_idrss":0,"ru_isrss":0,"ru_minflt":267,"ru_majflt":0,"ru_nswap":0,"ru_inblock":0,"ru_oublock":0,"ru_msgsnd":0,"ru_msgrcv":0,"ru_nsignals":0,"ru_nvcsw":25,"ru_nivcsw":83498}}
{"runtime":4695,"energy":{"pkg":240.80242919921875,"pp0":0,"dram":63.3582763671875},"rusage":{"ru_utime":{"tv_sec":14,"tv_usec":960979},"ru_stime":{"tv_sec":0,"tv_usec":124032},"ru_maxrss":3952,"ru_ixrss":0,"ru_idrss":0,"ru_isrss":0,"ru_minflt":268,"ru_majflt":0,"ru_nswap":0,"ru_inblock":0,"ru_oublock":0,"ru_msgsnd":0,"ru_msgrcv":0,"ru_nsignals":0,"ru_nvcsw":25,"ru_nivcsw":106112}}
{"runtime":3777,"energy":{"pkg":196.513916015625,"pp0":0,"dram":49.0509033203125},"rusage":{"ru_utime":{"tv_sec":13,"tv_usec":154882},"ru_stime":{"tv_sec":0,"tv_usec":75940},"ru_maxrss":3868,"ru_ixrss":0,"ru_idrss":0,"ru_isrss":0,"ru_minflt":263,"ru_majflt":0,"ru_nswap":0,"ru_inblock":0,"ru_oublock":0,"ru_msgsnd":0,"ru_msgrcv":0,"ru_nsignals":0,"ru_nvcsw":21,"ru_nivcsw":94315}}
