{"runtime":1555,"energy":{"pkg":46.1947021484375,"pp0":0,"dram":12.30853271484375},"rusage":{"ru_utime":{"tv_sec":1,"tv_usec":554453},"ru_stime":{"tv_sec":0,"tv_usec":0},"ru_maxrss":4592,"ru_ixrss":0,"ru_idrss":0,"ru_isrss":0,"ru_minflt":378,"ru_majflt":0,"ru_nswap":0,"ru_inblock":0,"ru_oublock":0,"ru_msgsnd":0,"ru_msgrcv":0,"ru_nsignals":0,"ru_nvcsw":4,"ru_nivcsw":157}}
{"runtime":1231,"energy":{"pkg":43.1260986328125,"pp0":0,"dram":9.76678466796875},"rusage":{"ru_utime":{"tv_sec":1,"tv_usec":230758},"ru_stime":{"tv_sec":0,"tv_usec":0},"ru_maxrss":4712,"ru_ixrss":0,"ru_idrss":0,"ru_isrss":0,"ru_minflt":381,"ru_majflt":0,"ru_nswap":0,"ru_inblock":0,"ru_oublock":0,"ru_msgsnd":0,"ru_msgrcv":0,"ru_nsignals":0,"ru_nvcsw":4,"ru_nivcsw":122}}
{"runtime":906,"energy":{"pkg":35.65264892578125,"pp0":0,"dram":7.1820068359375},"rusage":{"ru_utime":{"tv_sec":0,"tv_usec":905618},"ru_stime":{"tv_sec":0,"tv_usec":0},"ru_maxrss":4704,"ru_ixrss":0,"ru_idrss":0,"ru_isrss":0,"ru_minflt":379,"ru_majflt":0,"ru_nswap":0,"ru_inblock":0,"ru_oublock":0,"ru_msgsnd":0,"ru_msgrcv":0,"ru_nsignals":0,"ru_nvcsw":4,"ru_nivcsw":91}}
{"runtime":901,"energy":{"pkg":35.3453369140625,"pp0":0,"dram":7.09613037109375},"rusage":{"ru_utime":{"tv_sec":0,"tv_usec":896919},"ru_stime":{"tv_sec":0,"tv_usec":3998},"ru_maxrss":4656,"ru_ixrss":0,"ru_idrss":0,"ru_isrss":0,"ru_minflt":379,"ru_majflt":0,"ru_nswap":0,"ru_inblock":0,"ru_oublock":0,"ru_msgsnd":0,"ru_msgrcv":0,"ru_nsignals":0,"ru_nvcsw":4,"ru_nivcsw":91}}
{"runtime":903,"energy":{"pkg":35.4146728515625,"pp0":0,"dram":7.0382080078125},"rusage":{"ru_utime":{"tv_sec":0,"tv_usec":898531},"ru_stime":{"tv_sec":0,"tv_usec":3988},"ru_maxrss":4548,"ru_ixrss":0,"ru_idrss":0,"ru_isrss":0,"ru_minflt":378,"ru_majflt":0,"ru_nswap":0,"ru_inblock":0,"ru_oublock":0,"ru_msgsnd":0,"ru_msgrcv":0,"ru_nsignals":0,"ru_nvcsw":4,"ru_nivcsw":92}}
{"runtime":1162,"energy":{"pkg":43.042236328125,"pp0":0,"dram":9.13739013671875},"rusage":{"ru_utime":{"tv_sec":1,"tv_usec":160499},"ru_stime":{"tv_sec":0,"tv_usec":1192},"ru_maxrss":4572,"ru_ixrss":0,"ru_idrss":0,"ru_isrss":0,"ru_minflt":376,"ru_majflt":0,"ru_nswap":0,"ru_inblock":0,"ru_oublock":0,"ru_msgsnd":0,"ru_msgrcv":0,"ru_nsignals":0,"ru_nvcsw":4,"ru_nivcsw":119}}
{"runtime":1556,"energy":{"pkg":46.0191650390625,"pp0":0,"dram":11.8397216796875},"rusage":{"ru_utime":{"tv_sec":1,"tv_usec":552289},"ru_stime":{"tv_sec":0,"tv_usec":3997},"ru_maxrss":4656,"ru_ixrss":0,"ru_idrss":0,"ru_isrss":0,"ru_minflt":381,"ru_majflt":0,"ru_nswap":0,"ru_inblock":0,"ru_oublock":0,"ru_msgsnd":0,"ru_msgrcv":0,"ru_nsignals":0,"ru_nvcsw":4,"ru_nivcsw":159}}
{"runtime":1129,"energy":{"pkg":41.4312744140625,"pp0":0,"dram":8.885498046875},"rusage":{"ru_utime":{"tv_sec":1,"tv_usec":128022},"ru_stime":{"tv_sec":0,"tv_usec":1253},"ru_maxrss":4704,"ru_ixrss":0,"ru_idrss":0,"ru_isrss":0,"ru_minflt":379,"ru_majflt":0,"ru_nswap":0,"ru_inblock":0,"ru_oublock":0,"ru_msgsnd":0,"ru_msgrcv":0,"ru_nsignals":0,"ru_nvcsw":4,"ru_nivcsw":116}}
{"runtime":1138,"energy":{"pkg":42.31097412109375,"pp0":0,"dram":8.928466796875},"rusage":{"ru_utime":{"tv_sec":1,"tv_usec":138462},"ru_stime":{"tv_sec":0,"tv_usec":0},"ru_maxrss":4640,"ru_ixrss":0,"ru_idrss":0,"ru_isrss":0,"ru_minflt":378,"ru_majflt":0,"ru_nswap":0,"ru_inblock":0,"ru_oublock":0,"ru_msgsnd":0,"ru_msgrcv":0,"ru_nsignals":0,"ru_nvcsw":4,"ru_nivcsw":117}}
{"runtime":905,"energy":{"pkg":35.7396240234375,"pp0":0,"dram":7.12762451171875},"rusage":{"ru_utime":{"tv_sec":0,"tv_usec":900564},"ru_stime":{"tv_sec":0,"tv_usec":3997},"ru_maxrss":4580,"ru_ixrss":0,"ru_idrss":0,"ru_isrss":0,"ru_minflt":378,"ru_majflt":0,"ru_nswap":0,"ru_inblock":0,"ru_oublock":0,"ru_msgsnd":0,"ru_msgrcv":0,"ru_nsignals":0,"ru_nvcsw":4,"ru_nivcsw":91}}
{"runtime":904,"energy":{"pkg":35.67266845703125,"pp0":0,"dram":7.14361572265625},"rusage":{"ru_utime":{"tv_sec":0,"tv_usec":899830},"ru_stime":{"tv_sec":0,"tv_usec":3994},"ru_maxrss":4584,"ru_ixrss":0,"ru_idrss":0,"ru_isrss":0,"ru_minflt":377,"ru_majflt":0,"ru_nswap":0,"ru_inblock":0,"ru_oublock":0,"ru_msgsnd":0,"ru_msgrcv":0,"ru_nsignals":0,"ru_nvcsw":4,"ru_nivcsw":94}}
{"runtime":1495,"energy":{"pkg":45.57763671875,"pp0":0,"dram":11.75323486328125},"rusage":{"ru_utime":{"tv_sec":1,"tv_usec":495160},"ru_stime":{"tv_sec":0,"tv_usec":0},"ru_maxrss":4640,"ru_ixrss":0,"ru_idrss":0,"ru_isrss":0,"ru_minflt":378,"ru_majflt":0,"ru_nswap":0,"ru_inblock":0,"ru_oublock":0,"ru_msgsnd":0,"ru_msgrcv":0,"ru_nsignals":0,"ru_nvcsw":4,"ru_nivcsw":150}}
{"runtime":1542,"energy":{"pkg":47.11749267578125,"pp0":0,"dram":12.26263427734375},"rusage":{"ru_utime":{"tv_sec":1,"tv_usec":541341},"ru_stime":{"tv_sec":0,"tv_usec":0},"ru_maxrss":4580,"ru_ixrss":0,"ru_idrss":0,"ru_isrss":0,"ru_minflt":378,"ru_majflt":0,"ru_nswap":0,"ru_inblock":0,"ru_oublock":0,"ru_msgsnd":0,"ru_msgrcv":0,"ru_nsignals":0,"ru_nvcsw":4,"ru_nivcsw":154}}
{"runtime":1554,"energy":{"pkg":45.80718994140625,"pp0":0,"dram":12.32135009765625},"rusage":{"ru_utime":{"tv_sec":1,"tv_usec":553867},"ru_stime":{"tv_sec":0,"tv_usec":0},"ru_maxrss":4644,"ru_ixrss":0,"ru_idrss":0,"ru_isrss":0,"ru_minflt":379,"ru_majflt":0,"ru_nswap":0,"ru_inblock":0,"ru_oublock":0,"ru_msgsnd":0,"ru_msgrcv":0,"ru_nsignals":0,"ru_nvcsw":4,"ru_nivcsw":156}}
{"runtime":920,"energy":{"pkg":35.690185546875,"pp0":0,"dram":7.341552734375},"rusage":{"ru_utime":{"tv_sec":0,"tv_usec":916069},"ru_stime":{"tv_sec":0,"tv_usec":3995},"ru_maxrss":4712,"ru_ixrss":0,"ru_idrss":0,"ru_isrss":0,"ru_minflt":383,"ru_majflt":0,"ru_nswap":0,"ru_inblock":0,"ru_oublock":0,"ru_msgsnd":0,"ru_msgrcv":0,"ru_nsignals":0,"ru_nvcsw":4,"ru_nivcsw":91}}
{"runtime":898,"energy":{"pkg":35.436767578125,"pp0":0,"dram":7.13372802734375},"rusage":{"ru_utime":{"tv_sec":0,"tv_usec":898072},"ru_stime":{"tv_sec":0,"tv_usec":0},"ru_maxrss":4580,"ru_ixrss":0,"ru_idrss":0,"ru_isrss":0,"ru_minflt":378,"ru_majflt":0,"ru_nswap":0,"ru_inblock":0,"ru_oublock":0,"ru_msgsnd":0,"ru_msgrcv":0,"ru_nsignals":0,"ru_nvcsw":4,"ru_nivcsw":91}}
{"runtime":898,"energy":{"pkg":35.26953125,"pp0":0,"dram":7.14111328125},"rusage":{"ru_utime":{"tv_sec":0,"tv_usec":894140},"ru_stime":{"tv_sec":0,"tv_usec":4004},"ru_maxrss":4648,"ru_ixrss":0,"ru_idrss":0,"ru_isrss":0,"ru_minflt":379,"ru_majflt":0,"ru_nswap":0,"ru_inblock":0,"ru_oublock":0,"ru_msgsnd":0,"ru_msgrcv":0,"ru_nsignals":0,"ru_nvcsw":4,"ru_nivcsw":91}}
{"runtime":1568,"energy":{"pkg":46.97662353515625,"pp0":0,"dram":12.42291259765625},"rusage":{"ru_utime":{"tv_sec":1,"tv_usec":563541},"ru_stime":{"tv_sec":0,"tv_usec":3996},"ru_maxrss":4644,"ru_ixrss":0,"ru_idrss":0,"ru_isrss":0,"ru_minflt":378,"ru_majflt":0,"ru_nswap":0,"ru_inblock":0,"ru_oublock":0,"ru_msgsnd":0,"ru_msgrcv":0,"ru_nsignals":0,"ru_nvcsw":4,"ru_nivcsw":154}}
{"runtime":1232,"energy":{"pkg":43.00341796875,"pp0":0,"dram":9.7247314453125},"rusage":{"ru_utime":{"tv_sec":1,"tv_usec":231600},"ru_stime":{"tv_sec":0,"tv_usec":0},"ru_maxrss":4580,"ru_ixrss":0,"ru_idrss":0,"ru_isrss":0,"ru_minflt":377,"ru_majflt":0,"ru_nswap":0,"ru_inblock":0,"ru_oublock":0,"ru_msgsnd":0,"ru_msgrcv":0,"ru_nsignals":0,"ru_nvcsw":4,"ru_nivcsw":128}}
{"runtime":905,"energy":{"pkg":35.23834228515625,"pp0":0,"dram":7.104248046875},"rusage":{"ru_utime":{"tv_sec":0,"tv_usec":904850},"ru_stime":{"tv_sec":0,"tv_usec":0},"ru_maxrss":4712,"ru_ixrss":0,"ru_idrss":0,"ru_isrss":0,"ru_minflt":384,"ru_majflt":0,"ru_nswap":0,"ru_inblock":0,"ru_oublock":0,"ru_msgsnd":0,"ru_msgrcv":0,"ru_nsignals":0,"ru_nvcsw":4,"ru_nivcsw":88}}
{"runtime":1304,"energy":{"pkg":42.5006103515625,"pp0":0,"dram":10.2977294921875},"rusage":{"ru_utime":{"tv_sec":1,"tv_usec":299782},"ru_stime":{"tv_sec":0,"tv_usec":3996},"ru_maxrss":4636,"ru_ixrss":0,"ru_idrss":0,"ru_isrss":0,"ru_minflt":379,"ru_majflt":0,"ru_nswap":0,"ru_inblock":0,"ru_oublock":0,"ru_msgsnd":0,"ru_msgrcv":0,"ru_nsignals":0,"ru_nvcsw":4,"ru_nivcsw":133}}
