{"runtime_ms":92,"counters":{"PERF_COUNT_HW_CACHE_REFERENCES":1109237,"PERF_COUNT_HW_CACHE_MISSES":100338,"PERF_COUNT_SW_TASK_CLOCK":1050265223},"energy_samples":[{"duration_ms":93,"energy":{"pkg":14.51336669921875,"pp0":0,"dram":0.57208251953125}},{"duration_ms":93,"energy":{"pkg":18.21673583984375,"pp0":0,"dram":0.530029296875}}]}
{"runtime_ms":89,"counters":{"PERF_COUNT_HW_CACHE_REFERENCES":1049103,"PERF_COUNT_HW_CACHE_MISSES":92761,"PERF_COUNT_SW_TASK_CLOCK":1109852308},"energy_samples":[{"duration_ms":90,"energy":{"pkg":14.4429931640625,"pp0":0,"dram":0.5457763671875}},{"duration_ms":90,"energy":{"pkg":17.55133056640625,"pp0":0,"dram":0.507568359375}}]}
{"runtime_ms":95,"counters":{"PERF_COUNT_HW_CACHE_REFERENCES":1051599,"PERF_COUNT_HW_CACHE_MISSES":97223,"PERF_COUNT_SW_TASK_CLOCK":1208970306},"energy_samples":[{"duration_ms":96,"energy":{"pkg":15.6007080078125,"pp0":0,"dram":0.57904052734375}},{"duration_ms":96,"energy":{"pkg":18.61279296875,"pp0":0,"dram":0.542236328125}}]}
{"runtime_ms":88,"counters":{"PERF_COUNT_HW_CACHE_REFERENCES":1043196,"PERF_COUNT_HW_CACHE_MISSES":83112,"PERF_COUNT_SW_TASK_CLOCK":1100250290},"energy_samples":[{"duration_ms":89,"energy":{"pkg":14.56298828125,"pp0":0,"dram":0.54022216796875}},{"duration_ms":89,"energy":{"pkg":17.55224609375,"pp0":0,"dram":0.50030517578125}}]}
{"runtime_ms":90,"counters":{"PERF_COUNT_HW_CACHE_REFERENCES":1024388,"PERF_COUNT_HW_CACHE_MISSES":95198,"PERF_COUNT_SW_TASK_CLOCK":1127793831},"energy_samples":[{"duration_ms":90,"energy":{"pkg":14.93841552734375,"pp0":0,"dram":0.55633544921875}},{"duration_ms":90,"energy":{"pkg":17.54888916015625,"pp0":0,"dram":0.5087890625}}]}
{"runtime_ms":91,"counters":{"PERF_COUNT_HW_CACHE_REFERENCES":1035920,"PERF_COUNT_HW_CACHE_MISSES":88621,"PERF_COUNT_SW_TASK_CLOCK":1130676183},"energy_samples":[{"duration_ms":91,"energy":{"pkg":15.21185302734375,"pp0":0,"dram":0.55975341796875}},{"duration_ms":91,"energy":{"pkg":17.6099853515625,"pp0":0,"dram":0.515380859375}}]}
{"runtime_ms":94,"counters":{"PERF_COUNT_HW_CACHE_REFERENCES":1014658,"PERF_COUNT_HW_CACHE_MISSES":85111,"PERF_COUNT_SW_TASK_CLOCK":1211529195},"energy_samples":[{"duration_ms":94,"energy":{"pkg":15.6356201171875,"pp0":0,"dram":0.5625}},{"duration_ms":94,"energy":{"pkg":18.28619384765625,"pp0":0,"dram":0.5328369140625}}]}
{"runtime_ms":92,"counters":{"PERF_COUNT_HW_CACHE_REFERENCES":1031674,"PERF_COUNT_HW_CACHE_MISSES":94605,"PERF_COUNT_SW_TASK_CLOCK":1169717683},"energy_samples":[{"duration_ms":92,"energy":{"pkg":15.29241943359375,"pp0":0,"dram":0.56005859375}},{"duration_ms":92,"energy":{"pkg":17.83837890625,"pp0":0,"dram":0.509521484375}}]}
{"runtime_ms":85,"counters":{"PERF_COUNT_HW_CACHE_REFERENCES":1015050,"PERF_COUNT_HW_CACHE_MISSES":86815,"PERF_COUNT_SW_TASK_CLOCK":1055905583},"energy_samples":[{"duration_ms":85,"energy":{"pkg":14.32879638671875,"pp0":0,"dram":0.52484130859375}},{"duration_ms":85,"energy":{"pkg":17.060302734375,"pp0":0,"dram":0.4840087890625}}]}
{"runtime_ms":87,"counters":{"PERF_COUNT_HW_CACHE_REFERENCES":1062393,"PERF_COUNT_HW_CACHE_MISSES":80992,"PERF_COUNT_SW_TASK_CLOCK":1047010688},"energy_samples":[{"duration_ms":88,"energy":{"pkg":13.7137451171875,"pp0":0,"dram":0.529052734375}},{"duration_ms":88,"energy":{"pkg":17.32659912109375,"pp0":0,"dram":0.498046875}}]}
{"runtime_ms":94,"counters":{"PERF_COUNT_HW_CACHE_REFERENCES":1047604,"PERF_COUNT_HW_CACHE_MISSES":76613,"PERF_COUNT_SW_TASK_CLOCK":1159033291},"energy_samples":[{"duration_ms":94,"energy":{"pkg":14.98602294921875,"pp0":0,"dram":0.58221435546875}},{"duration_ms":94,"energy":{"pkg":18.17572021484375,"pp0":0,"dram":0.52947998046875}}]}
{"runtime_ms":92,"counters":{"PERF_COUNT_HW_CACHE_REFERENCES":1015680,"PERF_COUNT_HW_CACHE_MISSES":80868,"PERF_COUNT_SW_TASK_CLOCK":1171450896},"energy_samples":[{"duration_ms":92,"energy":{"pkg":15.04217529296875,"pp0":0,"dram":0.561767578125}},{"duration_ms":92,"energy":{"pkg":18.22723388671875,"pp0":0,"dram":0.52471923828125}}]}
{"runtime_ms":89,"counters":{"PERF_COUNT_HW_CACHE_REFERENCES":991247,"PERF_COUNT_HW_CACHE_MISSES":77801,"PERF_COUNT_SW_TASK_CLOCK":1141807159},"energy_samples":[{"duration_ms":89,"energy":{"pkg":14.37060546875,"pp0":0,"dram":0.538330078125}},{"duration_ms":89,"energy":{"pkg":17.705810546875,"pp0":0,"dram":0.50848388671875}}]}
{"runtime_ms":93,"counters":{"PERF_COUNT_HW_CACHE_REFERENCES":1056690,"PERF_COUNT_HW_CACHE_MISSES":83928,"PERF_COUNT_SW_TASK_CLOCK":1151925413},"energy_samples":[{"duration_ms":93,"energy":{"pkg":15.12542724609375,"pp0":0,"dram":0.5758056640625}},{"duration_ms":93,"energy":{"pkg":17.8603515625,"pp0":0,"dram":0.5316162109375}}]}
{"runtime_ms":95,"counters":{"PERF_COUNT_HW_CACHE_REFERENCES":1027431,"PERF_COUNT_HW_CACHE_MISSES":87269,"PERF_COUNT_SW_TASK_CLOCK":1213546758},"energy_samples":[{"duration_ms":95,"energy":{"pkg":15.53179931640625,"pp0":0,"dram":0.5872802734375}},{"duration_ms":95,"energy":{"pkg":18.1533203125,"pp0":0,"dram":0.5372314453125}}]}
{"runtime_ms":89,"counters":{"PERF_COUNT_HW_CACHE_REFERENCES":998926,"PERF_COUNT_HW_CACHE_MISSES":85934,"PERF_COUNT_SW_TASK_CLOCK":1135219814},"energy_samples":[{"duration_ms":89,"energy":{"pkg":14.8614501953125,"pp0":0,"dram":0.5418701171875}},{"duration_ms":89,"energy":{"pkg":17.35943603515625,"pp0":0,"dram":0.50396728515625}}]}
{"runtime_ms":118,"counters":{"PERF_COUNT_HW_CACHE_REFERENCES":1034603,"PERF_COUNT_HW_CACHE_MISSES":77613,"PERF_COUNT_SW_TASK_CLOCK":1575364940},"energy_samples":[{"duration_ms":118,"energy":{"pkg":17.7412109375,"pp0":0,"dram":0.7005615234375}},{"duration_ms":118,"energy":{"pkg":22.6754150390625,"pp0":0,"dram":0.67279052734375}}]}
{"runtime_ms":90,"counters":{"PERF_COUNT_HW_CACHE_REFERENCES":1049134,"PERF_COUNT_HW_CACHE_MISSES":85760,"PERF_COUNT_SW_TASK_CLOCK":1111330751},"energy_samples":[{"duration_ms":90,"energy":{"pkg":14.43890380859375,"pp0":0,"dram":0.556640625}},{"duration_ms":90,"energy":{"pkg":17.68780517578125,"pp0":0,"dram":0.506103515625}}]}
{"runtime_ms":95,"counters":{"PERF_COUNT_HW_CACHE_REFERENCES":1014293,"PERF_COUNT_HW_CACHE_MISSES":12108,"PERF_COUNT_SW_TASK_CLOCK":1224471076},"energy_samples":[{"duration_ms":95,"energy":{"pkg":14.718017578125,"pp0":0,"dram":0.57904052734375}},{"duration_ms":95,"energy":{"pkg":18.02374267578125,"pp0":0,"dram":0.53326416015625}}]}
{"runtime_ms":93,"counters":{"PERF_COUNT_HW_CACHE_REFERENCES":1033524,"PERF_COUNT_HW_CACHE_MISSES":91367,"PERF_COUNT_SW_TASK_CLOCK":1211214437},"energy_samples":[{"duration_ms":93,"energy":{"pkg":15.5426025390625,"pp0":0,"dram":0.569091796875}},{"duration_ms":93,"energy":{"pkg":17.58343505859375,"pp0":0,"dram":0.52557373046875}}]}
{"runtime_ms":93,"counters":{"PERF_COUNT_HW_CACHE_REFERENCES":1041961,"PERF_COUNT_HW_CACHE_MISSES":71983,"PERF_COUNT_SW_TASK_CLOCK":1142912579},"energy_samples":[{"duration_ms":93,"energy":{"pkg":15.30645751953125,"pp0":0,"dram":0.5594482421875}},{"duration_ms":93,"energy":{"pkg":17.90399169921875,"pp0":0,"dram":0.52191162109375}}]}
